creditpulse/__init__.py
creditpulse/check.py
creditpulse/bases_externas/__init__.py
creditpulse/bases_externas/database.py
creditpulse/bases_externas/schema.py
creditpulse/bases_externas/truora.py
creditpulse/cli/__init__.py
creditpulse/cli/commands.py
creditpulse/common/__init__.py
creditpulse/common/error_messages.py
creditpulse/requests/__init__.py
creditpulse/requests/request_manager.py
creditpulse-0.1.10.dist-info/licenses/LICENSE
test/__init__.py
test/test_back_off.py
test/test_truora_check.py
creditpulse-0.1.10.dist-info/METADATA
creditpulse-0.1.10.dist-info/WHEEL
creditpulse-0.1.10.dist-info/entry_points.txt
creditpulse-0.1.10.dist-info/top_level.txt
creditpulse-0.1.10.dist-info/RECORD
