Metadata-Version: 2.4
Name: creditpulse
Version: 0.1.10
Summary: A pyhton library for financial analysis with external databases
Author-email: Santiago Velez <s.velez@saman-wm.com>
Requires-Python: >=3.7
License-File: LICENSE
Requires-Dist: click==8.1.8
Requires-Dist: requests==2.32.4
Requires-Dist: pydantic==2.8.0
Requires-Dist: pylint==3.3.7
Dynamic: license-file
